{"problemId": 24672, "titleKo": "Maximal Subsequence", "titles": [{"language": "en", "languageDisplayName": "en", "title": "Maximal Subsequence", "isOriginal": true}], "isSolvable": true, "isPartial": false, "acceptedUserCount": 16, "level": 24, "votedUserCount": 2, "sprout": false, "givesNoRating": false, "isLevelLocked": false, "averageTries": 2.0625, "official": true, "tags": [{"key": "ad_hoc", "isMeta": false, "bojTagId": 109, "problemCount": 1424, "displayNames": [{"language": "ko", "name": "\uc560\ub4dc \ud639", "short": "\uc560\ub4dc \ud639"}, {"language": "en", "name": "ad-hoc", "short": "ad-hoc"}, {"language": "ja", "name": "\u30a2\u30c9\u30db\u30c3\u30af", "short": "\u30a2\u30c9\u30db\u30c3\u30af"}], "aliases": []}, {"key": "flow", "isMeta": false, "bojTagId": 45, "problemCount": 322, "displayNames": [{"language": "ko", "name": "\ucd5c\ub300 \uc720\ub7c9", "short": "\ucd5c\ub300 \uc720\ub7c9"}, {"language": "en", "name": "maximum flow", "short": "flow"}, {"language": "ja", "name": "\u6700\u5927\u30d5\u30ed\u30fc", "short": "flow"}], "aliases": [{"alias": "dinic"}, {"alias": "dinitz"}, {"alias": "ford"}, {"alias": "fulkerson"}, {"alias": "fordfulkerson"}, {"alias": "\ub514\ub2c9"}, {"alias": "\ub514\ub2c8\uce20"}, {"alias": "\ud3ec\ub4dc\ud480\ucee4\uc2a8"}, {"alias": "\ud50c\ub85c\uc6b0"}]}, {"key": "lis", "isMeta": false, "bojTagId": 43, "problemCount": 85, "displayNames": [{"language": "ko", "name": "\uac00\uc7a5 \uae34 \uc99d\uac00\ud558\ub294 \ubd80\ubd84 \uc218\uc5f4: O(n log n)", "short": "\uac00\uc7a5 \uae34 \uc99d\uac00\ud558\ub294 \ubd80\ubd84 \uc218\uc5f4: O(n log n)"}, {"language": "en", "name": "longest increasing sequence in o(n log n)", "short": "lis in o(n log n)"}, {"language": "ja", "name": "longest increasing sequence in o(n log n)", "short": "lis in o(n log n)"}], "aliases": []}, {"key": "mfmc", "isMeta": false, "bojTagId": 167, "problemCount": 71, "displayNames": [{"language": "ko", "name": "\ucd5c\ub300 \uc720\ub7c9 \ucd5c\uc18c \ucef7 \uc815\ub9ac", "short": "\ucd5c\ub300 \uc720\ub7c9 \ucd5c\uc18c \ucef7 \uc815\ub9ac"}, {"language": "en", "name": "max-flow min-cut theorem", "short": "mfmc"}, {"language": "ja", "name": "\u6700\u5927\u30d5\u30ed\u30fc\u6700\u5c0f\u30ab\u30c3\u30c8\u5b9a\u7406", "short": "mfmc"}], "aliases": []}], "metadata": {}}