{"problemId": 14360, "titleKo": "The Gardener of Seville (Large)", "titles": [{"language": "en", "languageDisplayName": "en", "title": "The Gardener of Seville (Large)", "isOriginal": true}], "isSolvable": true, "isPartial": false, "acceptedUserCount": 8, "level": 20, "votedUserCount": 3, "sprout": false, "givesNoRating": false, "isLevelLocked": false, "averageTries": 2.75, "official": true, "tags": [{"key": "ad_hoc", "isMeta": false, "bojTagId": 109, "problemCount": 1423, "displayNames": [{"language": "ko", "name": "\uc560\ub4dc \ud639", "short": "\uc560\ub4dc \ud639"}, {"language": "en", "name": "ad-hoc", "short": "ad-hoc"}, {"language": "ja", "name": "\u30a2\u30c9\u30db\u30c3\u30af", "short": "\u30a2\u30c9\u30db\u30c3\u30af"}], "aliases": []}, {"key": "greedy", "isMeta": false, "bojTagId": 33, "problemCount": 2452, "displayNames": [{"language": "ko", "name": "\uadf8\ub9ac\ub514 \uc54c\uace0\ub9ac\uc998", "short": "\uadf8\ub9ac\ub514 \uc54c\uace0\ub9ac\uc998"}, {"language": "en", "name": "greedy", "short": "greedy"}, {"language": "ja", "name": "\u8caa\u6b32\u6cd5", "short": "\u8caa\u6b32\u6cd5"}], "aliases": [{"alias": "\ud0d0\uc695\ubc95"}]}, {"key": "implementation", "isMeta": false, "bojTagId": 102, "problemCount": 5379, "displayNames": [{"language": "ko", "name": "\uad6c\ud604", "short": "\uad6c\ud604"}, {"language": "en", "name": "implementation", "short": "impl"}, {"language": "ja", "name": "\u5b9f\u88c5", "short": "impl"}], "aliases": []}, {"key": "simulation", "isMeta": false, "bojTagId": 141, "problemCount": 1049, "displayNames": [{"language": "ko", "name": "\uc2dc\ubbac\ub808\uc774\uc158", "short": "\uc2dc\ubbac\ub808\uc774\uc158"}, {"language": "en", "name": "simulation", "short": "simulation"}, {"language": "ja", "name": "\u30b7\u30df\u30e5\u30ec\u30fc\u30b7\u30e7\u30f3", "short": "\u30b7\u30df\u30e5\u30ec\u30fc\u30b7\u30e7\u30f3"}], "aliases": []}], "metadata": {}}