{"problemId": 17381, "titleKo": "\ubbf8\ub85c", "titles": [{"language": "ko", "languageDisplayName": "ko", "title": "\ubbf8\ub85c", "isOriginal": true}], "isSolvable": true, "isPartial": false, "acceptedUserCount": 3, "level": 28, "votedUserCount": 1, "sprout": false, "givesNoRating": false, "isLevelLocked": false, "averageTries": 1, "official": true, "tags": [{"key": "graphs", "isMeta": false, "bojTagId": 7, "problemCount": 3583, "displayNames": [{"language": "ko", "name": "\uadf8\ub798\ud504 \uc774\ub860", "short": "\uadf8\ub798\ud504 \uc774\ub860"}, {"language": "en", "name": "graph theory", "short": "graph"}, {"language": "ja", "name": "\u30b0\u30e9\u30d5\u7406\u8ad6", "short": "\u30b0\u30e9\u30d5"}], "aliases": [{"alias": "\uadf8\ub798\ud504\uc774\ub860"}, {"alias": "\uadf8\ub798\ud504"}]}, {"key": "hld", "isMeta": false, "bojTagId": 35, "problemCount": 81, "displayNames": [{"language": "ko", "name": "Heavy-light \ubd84\ud560", "short": "Heavy-light \ubd84\ud560"}, {"language": "en", "name": "heavy-light decomposition", "short": "hld"}, {"language": "ja", "name": "heavy-light decomposition", "short": "hld"}], "aliases": []}, {"key": "scc", "isMeta": false, "bojTagId": 76, "problemCount": 146, "displayNames": [{"language": "ko", "name": "\uac15\ud55c \uc5f0\uacb0 \uc694\uc18c", "short": "\uac15\ud55c \uc5f0\uacb0 \uc694\uc18c"}, {"language": "en", "name": "strongly connected component", "short": "scc"}, {"language": "ja", "name": "\u5f37\u9023\u7d50", "short": "\u5f37\u9023\u7d50"}], "aliases": []}, {"key": "trees", "isMeta": false, "bojTagId": 120, "problemCount": 1356, "displayNames": [{"language": "ko", "name": "\ud2b8\ub9ac", "short": "\ud2b8\ub9ac"}, {"language": "en", "name": "tree", "short": "tree"}, {"language": "ja", "name": "\u6728", "short": "\u6728"}], "aliases": [{"alias": "trees"}]}], "metadata": {}}