{"problemId": 20144, "titleKo": "Vista 7", "titles": [{"language": "en", "languageDisplayName": "en", "title": "Vista 7", "isOriginal": true}], "isSolvable": true, "isPartial": false, "acceptedUserCount": 9, "level": 0, "votedUserCount": 1, "sprout": false, "givesNoRating": false, "isLevelLocked": false, "averageTries": 1.3333, "official": true, "tags": [{"key": "ad_hoc", "isMeta": false, "bojTagId": 109, "problemCount": 1424, "displayNames": [{"language": "ko", "name": "\uc560\ub4dc \ud639", "short": "\uc560\ub4dc \ud639"}, {"language": "en", "name": "ad-hoc", "short": "ad-hoc"}, {"language": "ja", "name": "\u30a2\u30c9\u30db\u30c3\u30af", "short": "\u30a2\u30c9\u30db\u30c3\u30af"}], "aliases": []}, {"key": "heuristics", "isMeta": false, "bojTagId": 142, "problemCount": 100, "displayNames": [{"language": "ko", "name": "\ud734\ub9ac\uc2a4\ud2f1", "short": "\ud734\ub9ac\uc2a4\ud2f1"}, {"language": "en", "name": "heuristics", "short": "heuristics"}, {"language": "ja", "name": "\u30d2\u30e5\u30fc\u30ea\u30b9\u30c6\u30a3\u30c3\u30af", "short": "\u30d2\u30e5\u30fc\u30ea\u30b9\u30c6\u30a3\u30c3\u30af"}], "aliases": []}, {"key": "precomputation", "isMeta": false, "bojTagId": 172, "problemCount": 203, "displayNames": [{"language": "ko", "name": "\ub7f0\ud0c0\uc784 \uc804\uc758 \uc804\ucc98\ub9ac", "short": "\ub7f0\ud0c0\uc784 \uc804\uc758 \uc804\ucc98\ub9ac"}, {"language": "en", "name": "precomputation", "short": "precomputation"}, {"language": "ja", "name": "\u4e8b\u524d\u8a08\u7b97", "short": "\u4e8b\u524d\u8a08\u7b97"}], "aliases": [{"alias": "lookup table"}, {"alias": "db"}, {"alias": "database"}]}, {"key": "tsp", "isMeta": false, "bojTagId": 138, "problemCount": 58, "displayNames": [{"language": "ko", "name": "\uc678\ud310\uc6d0 \uc21c\ud68c \ubb38\uc81c", "short": "\uc678\ud310\uc6d0 \uc21c\ud68c \ubb38\uc81c"}, {"language": "en", "name": "travelling salesman problem", "short": "tsp"}, {"language": "ja", "name": "\u5de1\u56de\u30bb\u30fc\u30eb\u30b9\u30de\u30f3\u554f\u984c", "short": "\u5de1\u56de\u30bb\u30fc\u30eb\u30b9\u30de\u30f3"}], "aliases": [{"alias": "\uc678\ud310\uc6d0\uc21c\ud68c"}]}], "metadata": {}}