{"problemId": 21548, "titleKo": "\u0414\u043e\u043a\u043b\u0430\u0434 \u0438\u043d\u0432\u0435\u0441\u0442\u043e\u0440\u0430\u043c", "titles": [{"language": "ru", "languageDisplayName": "ru", "title": "\u0414\u043e\u043a\u043b\u0430\u0434 \u0438\u043d\u0432\u0435\u0441\u0442\u043e\u0440\u0430\u043c", "isOriginal": true}], "isSolvable": true, "isPartial": false, "acceptedUserCount": 11, "level": 25, "votedUserCount": 1, "sprout": false, "givesNoRating": false, "isLevelLocked": false, "averageTries": 6.8182, "official": true, "tags": [], "metadata": {}}