{"problemId": 30926, "titleKo": "\ud30c\ud2f0", "titles": [{"language": "ko", "languageDisplayName": "ko", "title": "\ud30c\ud2f0", "isOriginal": true}], "isSolvable": true, "isPartial": false, "acceptedUserCount": 1, "level": 27, "votedUserCount": 1, "sprout": false, "givesNoRating": false, "isLevelLocked": false, "averageTries": 1, "official": true, "tags": [{"key": "data_structures", "isMeta": false, "bojTagId": 175, "problemCount": 3730, "displayNames": [{"language": "ko", "name": "\uc790\ub8cc \uad6c\uc870", "short": "\uc790\ub8cc \uad6c\uc870"}, {"language": "en", "name": "data structures", "short": "ds"}, {"language": "ja", "name": "\u30c7\u30fc\u30bf\u69cb\u9020", "short": "ds"}], "aliases": [{"alias": "\uc790\ub8cc\uad6c\uc870"}, {"alias": "\uc790\uad6c"}]}, {"key": "greedy", "isMeta": false, "bojTagId": 33, "problemCount": 2460, "displayNames": [{"language": "ko", "name": "\uadf8\ub9ac\ub514 \uc54c\uace0\ub9ac\uc998", "short": "\uadf8\ub9ac\ub514 \uc54c\uace0\ub9ac\uc998"}, {"language": "en", "name": "greedy", "short": "greedy"}, {"language": "ja", "name": "\u8caa\u6b32\u6cd5", "short": "\u8caa\u6b32\u6cd5"}], "aliases": [{"alias": "\ud0d0\uc695\ubc95"}]}, {"key": "hall", "isMeta": false, "bojTagId": 34, "problemCount": 20, "displayNames": [{"language": "ko", "name": "\ud640\uc758 \uacb0\ud63c \uc815\ub9ac", "short": "\ud640\uc758 \uacb0\ud63c \uc815\ub9ac"}, {"language": "en", "name": "hall's theorem", "short": "hall's thm"}, {"language": "ja", "name": "\u30db\u30fc\u30eb\u306e\u5b9a\u7406", "short": "\u30db\u30fc\u30eb\u306e\u5b9a\u7406"}], "aliases": []}, {"key": "implementation", "isMeta": false, "bojTagId": 102, "problemCount": 5397, "displayNames": [{"language": "ko", "name": "\uad6c\ud604", "short": "\uad6c\ud604"}, {"language": "en", "name": "implementation", "short": "impl"}, {"language": "ja", "name": "\u5b9f\u88c5", "short": "impl"}], "aliases": []}, {"key": "matroid", "isMeta": false, "bojTagId": 104, "problemCount": 13, "displayNames": [{"language": "ko", "name": "\ub9e4\ud2b8\ub85c\uc774\ub4dc", "short": "\ub9e4\ud2b8\ub85c\uc774\ub4dc"}, {"language": "en", "name": "matroid", "short": "matroid"}, {"language": "ja", "name": "\u30de\u30c8\u30ed\u30a4\u30c9", "short": "\u30de\u30c8\u30ed\u30a4\u30c9"}], "aliases": []}, {"key": "segtree", "isMeta": false, "bojTagId": 65, "problemCount": 1272, "displayNames": [{"language": "ko", "name": "\uc138\uadf8\uba3c\ud2b8 \ud2b8\ub9ac", "short": "\uc138\uadf8\uba3c\ud2b8 \ud2b8\ub9ac"}, {"language": "en", "name": "segment tree", "short": "segtree"}, {"language": "ja", "name": "\u30bb\u30b0\u30e1\u30f3\u30c8\u6728", "short": "\u30bb\u30b0\u6728"}], "aliases": [{"alias": "\uad6c\uac04\ud2b8\ub9ac"}, {"alias": "\uc138\uadf8\ud2b8\ub9ac"}, {"alias": "fenwick"}, {"alias": "\ud39c\uc705"}]}], "metadata": {}}