{"problemId": 15722, "titleKo": "\ube59\uae00\ube59\uae00 \uc2a4\ub124\uc77c", "titles": [{"language": "ko", "languageDisplayName": "ko", "title": "\ube59\uae00\ube59\uae00 \uc2a4\ub124\uc77c", "isOriginal": true}], "isSolvable": true, "isPartial": false, "acceptedUserCount": 277, "level": 5, "votedUserCount": 14, "sprout": false, "givesNoRating": false, "isLevelLocked": false, "averageTries": 1.4838, "official": true, "tags": [{"key": "implementation", "isMeta": false, "bojTagId": 102, "problemCount": 5379, "displayNames": [{"language": "ko", "name": "\uad6c\ud604", "short": "\uad6c\ud604"}, {"language": "en", "name": "implementation", "short": "impl"}, {"language": "ja", "name": "\u5b9f\u88c5", "short": "impl"}], "aliases": []}], "metadata": {}}